ecode/__init__.py
ecode/ecode.py
ecode/ecode_decoder.py
ecode/ecode_encoder.py
ecode-0.1.5.dist-info/LICENSE
ecode-0.1.5.dist-info/WHEEL
ecode-0.1.5.dist-info/METADATA
ecode-0.1.5.dist-info/RECORD
