Metadata-Version: 2.1
Name: ecode
Version: 0.1.5
Summary: 
Home-page: https://github.com/emoji-gen/ecode-py
License: MIT
Author: Emoji Generator
Author-email: ultimate.emoji.gen@gmail.com
Maintainer: Emoji Generator
Maintainer-email: ultimate.emoji.gen@gmail.com
Requires-Python: >=3.6,<4.0
Classifier: Development Status :: 4 - Beta
Classifier: License :: OSI Approved :: MIT License
Classifier: Operating System :: OS Independent
Classifier: Programming Language :: Python :: 3
Classifier: Programming Language :: Python :: 3 :: Only
Classifier: Programming Language :: Python :: 3.6
Classifier: Programming Language :: Python :: 3.7
Classifier: Programming Language :: Python :: 3.8
Project-URL: Issue tracker, https://github.com/emoji-gen/ecode-py/issues
Project-URL: Repository, https://github.com/emoji-gen/ecode-py
